helixcommit/__init__.py
helixcommit/bitbucket_client.py
helixcommit/cache.py
helixcommit/changelog.py
helixcommit/cli.py
helixcommit/commit_generator.py
helixcommit/config.py
helixcommit/git_client.py
helixcommit/github_client.py
helixcommit/gitlab_client.py
helixcommit/grouper.py
helixcommit/models.py
helixcommit/parser.py
helixcommit/prompts.py
helixcommit/summarizer.py
helixcommit/template.py
helixcommit/utils.py
helixcommit/formatters/html.py
helixcommit/formatters/json.py
helixcommit/formatters/markdown.py
helixcommit/formatters/text.py
helixcommit/formatters/yaml.py
helixcommit/templates/html.j2
helixcommit/templates/json.j2
helixcommit/templates/markdown.j2
helixcommit/templates/text.j2
helixcommit/templates/yaml.j2
helixcommit/ui/__init__.py
helixcommit/ui/console.py
helixcommit/ui/panels.py
helixcommit/ui/spinners.py
helixcommit/ui/tables.py
helixcommit/ui/themes.py
helixcommit-1.2.4.dist-info/licenses/LICENSE
helixcommit-1.2.4.dist-info/METADATA
helixcommit-1.2.4.dist-info/WHEEL
helixcommit-1.2.4.dist-info/entry_points.txt
helixcommit-1.2.4.dist-info/top_level.txt
helixcommit-1.2.4.dist-info/RECORD
