Metadata-Version: 2.4
Name: helixcommit
Version: 1.2.4
Summary: Automated release notes generator for Git repositories.
Author: HelixCommit
License-Expression: MIT
Project-URL: Homepage, https://github.com/bjornefisk/HelixCommit
Project-URL: Repository, https://github.com/bjornefisk/HelixCommit
Requires-Python: >=3.9
License-File: LICENSE
Requires-Dist: GitPython>=3.1.43
Requires-Dist: Typer>=0.12.0
Requires-Dist: Jinja2>=3.1.2
Requires-Dist: requests>=2.32.3
Requires-Dist: PyGithub>=2.3.0
Requires-Dist: openai>=1.52.0
Requires-Dist: python-dateutil>=2.9.0
Requires-Dist: tomli>=2.0.0; python_version < "3.11"
Requires-Dist: pyyaml>=6.0
Requires-Dist: rich>=13.0.0
Requires-Dist: prompt_toolkit>=3.0.0
Requires-Dist: pyperclip>=1.8.0
Provides-Extra: dev
Requires-Dist: pytest>=8.3.3; extra == "dev"
Requires-Dist: pytest-mock>=3.14.0; extra == "dev"
Requires-Dist: pytest-cov>=5.0.0; extra == "dev"
Requires-Dist: responses>=0.25.3; extra == "dev"
Requires-Dist: ruff>=0.6.9; extra == "dev"
Requires-Dist: mypy>=1.13.0; extra == "dev"
Dynamic: license-file
